CONTRIBUTING.rst
HISTORY.rst
LICENSE
MANIFEST.in
README.rst
setup.cfg
setup.py
docs/Makefile
docs/conf.py
docs/contributing.rst
docs/history.rst
docs/index.rst
docs/installation.rst
docs/kie_server_py.rst
docs/make.bat
docs/modules.rst
docs/readme.rst
docs/usage.rst
docs/_build/html/_static/ajax-loader.gif
docs/_build/html/_static/comment-bright.png
docs/_build/html/_static/comment-close.png
docs/_build/html/_static/comment.png
docs/_build/html/_static/down-pressed.png
docs/_build/html/_static/down.png
docs/_build/html/_static/file.png
docs/_build/html/_static/minus.png
docs/_build/html/_static/plus.png
docs/_build/html/_static/up-pressed.png
docs/_build/html/_static/up.png
kie_server_py/__init__.py
kie_server_py/kie_server_py.py
kie_server_py.egg-info/PKG-INFO
kie_server_py.egg-info/SOURCES.txt
kie_server_py.egg-info/dependency_links.txt
kie_server_py.egg-info/not-zip-safe
kie_server_py.egg-info/requires.txt
kie_server_py.egg-info/top_level.txt
tests/__init__.py
tests/test_kie_server_py.py